trustlib/__init__.py
trustlib/utils/__init__.py
trustlib/utils/utils.py
trustlib-0.0.1.dist-info/LICENSE
trustlib-0.0.1.dist-info/METADATA
trustlib-0.0.1.dist-info/WHEEL
trustlib-0.0.1.dist-info/top_level.txt
trustlib-0.0.1.dist-info/RECORD
